LICENSE.txt
MANIFEST.in
README.md
cattle.py
requirements.txt
setup.py
cattle.egg-info/PKG-INFO
cattle.egg-info/SOURCES.txt
cattle.egg-info/dependency_links.txt
cattle.egg-info/entry_points.txt
cattle.egg-info/requires.txt
cattle.egg-info/top_level.txt