Metadata-Version: 1.0
Name: cattle
Version: 0.2.1
Summary: Python API and CLI for Cattle
Home-page: https://github.com/cattleio/cattle-cli
Author: Darren Shepherd
Author-email: darren.s.shepherd@gmail.com
License: MIT Style
Platform: UNKNOWN
